wtf_peewee-3.0.7.dist-info/licenses/LICENSE
wtfpeewee/__init__.py
wtfpeewee/_compat.py
wtfpeewee/fields.py
wtfpeewee/orm.py
wtfpeewee/tests.py
wtf_peewee-3.0.7.dist-info/METADATA
wtf_peewee-3.0.7.dist-info/WHEEL
wtf_peewee-3.0.7.dist-info/top_level.txt
wtf_peewee-3.0.7.dist-info/RECORD
