Metadata-Version: 2.4
Name: wtf-peewee
Version: 3.0.7
Summary: wtforms integration for peewee
Author-email: Charles Leifer <coleifer@gmail.com>
Project-URL: Repository, https://github.com/coleifer/wtf-peewee
Classifier: Environment :: Web Environment
Classifier: Programming Language :: Python :: 2
Classifier: Programming Language :: Python :: 3
Classifier: Topic :: Internet :: WWW/HTTP :: Dynamic Content
Classifier: Topic :: Software Development :: Libraries :: Python Modules
License-File: LICENSE
Requires-Dist: wtforms
Requires-Dist: peewee>=3.0.0
Dynamic: license-file
